dist/open_tab_tracker-0.0.1.tar.gz
open_tab_tracker/Platform.py
open_tab_tracker/__about__.py
open_tab_tracker/__init__.py
open_tab_tracker/__main__.py
open_tab_tracker/database.py
open_tab_tracker/graphing.py
open_tab_tracker/install.py
open_tab_tracker/browsers/Browser.py
open_tab_tracker/browsers/Chrome.py
open_tab_tracker/browsers/Firefox.py
open_tab_tracker/browsers/Safari.py
open_tab_tracker/browsers/__init__.py
open_tab_tracker-0.0.1.dist-info/METADATA
open_tab_tracker-0.0.1.dist-info/WHEEL
open_tab_tracker-0.0.1.dist-info/entry_points.txt
open_tab_tracker-0.0.1.dist-info/licenses/LICENSE.md
open_tab_tracker-0.0.1.dist-info/RECORD
