Metadata-Version: 2.1
Name: open-tab-tracker
Version: 0.0.1
Summary: Graphs how many open tabs you have in your browsers.
Project-URL: Source Code, https://github.com/alichtman/open_tab_tracker
Project-URL: Issue Tracker, https://github.com/alichtman/open_tab_tracker/issues
Author-email: Aaron Lichtman <aaronlichtman@gmail.com>
License-Expression: MIT
License-File: LICENSE.md
Keywords: browser,chrome,firefox,tab,tracking
Requires-Python: >=3.10
Requires-Dist: better-exceptions
Requires-Dist: black
Requires-Dist: click
Requires-Dist: jq
Requires-Dist: loguru
Requires-Dist: lz4
Requires-Dist: pandas
Requires-Dist: plotly
Requires-Dist: python-crontab
Requires-Dist: rich
Requires-Dist: rope
Requires-Dist: xdg-base-dirs
